streamlit_d3graph/__init__.py
streamlit_d3graph-1.0.3.dist-info/LICENSE
streamlit_d3graph-1.0.3.dist-info/LICENSE-d3graph
streamlit_d3graph-1.0.3.dist-info/METADATA
streamlit_d3graph-1.0.3.dist-info/WHEEL
streamlit_d3graph-1.0.3.dist-info/top_level.txt
streamlit_d3graph-1.0.3.dist-info/RECORD
