Metadata-Version: 2.1
Name: streamlit-d3graph
Version: 1.0.3
Summary: A simple component to display d3graph network graphs in Streamlit apps.
Home-page: https://github.com/snehankekre/streamlit-d3graph
Author: Snehan Kekre
Author-email: contact@snehankekre.com
License: MIT
Classifier: Programming Language :: Python :: 3
Classifier: Operating System :: OS Independent
Requires-Python: >=3.8
License-File: LICENSE
License-File: LICENSE-d3graph
Requires-Dist: d3graph >=2.4.10
Requires-Dist: streamlit
Requires-Dist: seaborn
